pypca/__init__.py
pypca/__main__.py
pypca/constants.py
pypca/exceptions.py
pypca/scanner.py
pypca-0.0.13.dist-info/LICENSE
pypca-0.0.13.dist-info/METADATA
pypca-0.0.13.dist-info/WHEEL
pypca-0.0.13.dist-info/entry_points.txt
pypca-0.0.13.dist-info/top_level.txt
pypca-0.0.13.dist-info/RECORD
