Metadata-Version: 2.1
Name: pypca
Version: 0.0.13
Summary: A python cli for PCA 301 smart plugs.
Home-page: http://www.github.com/majuss/pypca
Author: Majuss
License: MIT
Keywords: smart home automation
Platform: any
Requires-Python: >=3.5
Requires-Dist: pyserial
Requires-Dist: colorlog
